vjer/__init__.py
vjer/__main__.py
vjer/build.py
vjer/deploy.py
vjer/freeze.py
vjer/pre_release.py
vjer/py.typed
vjer/release.py
vjer/rollback.py
vjer/test.py
vjer/tool_reporter.py
vjer/utils.py
vjer/vjer.py
vjer-39.0.1.dist-info/entry_points.txt
vjer-39.0.1.dist-info/licenses/LICENSE
vjer-39.0.1.dist-info/WHEEL
vjer-39.0.1.dist-info/METADATA
vjer-39.0.1.dist-info/RECORD
